rtofdata/__init__.py
rtofdata/datasource/__init__.py
rtofdata/datasource/in_memory.py
rtofdata/erd.py
rtofdata/eventstream/__init__.py
rtofdata/excel.py
rtofdata/fake/__init__.py
rtofdata/fake/__main__.py
rtofdata/fake/faker.py
rtofdata/fake/generators.py
rtofdata/fake/output.py
rtofdata/fake/serialization.py
rtofdata/fake/sql.py
rtofdata/jekyll.py
rtofdata/parser/__init__.py
rtofdata/parser/__main__.py
rtofdata/parser/parser.py
rtofdata/specification/__init__.py
rtofdata/specification/data.py
rtofdata/specification/download.py
rtofdata/specification/parser.py
rtofdata/util/__init__.py
rtofdata/util/config.py
rtofdata/util/error_handler.py
rtofdata/validation/__init__.py
rtofdata/validation/validators/__init__.py
rtofdata/word.py
rtofdata-0.2.4.dist-info/METADATA
rtofdata-0.2.4.dist-info/WHEEL
rtofdata-0.2.4.dist-info/RECORD
